p4runtime_sh/__init__.py
p4runtime_sh/__main__.py
p4runtime_sh/bytes_utils.py
p4runtime_sh/context.py
p4runtime_sh/global_options.py
p4runtime_sh/p4runtime.py
p4runtime_sh/shell.py
p4runtime_sh/test.py
p4runtime_sh/utils.py
p4runtime_shell-0.0.5.dist-info/licenses/LICENSE
p4runtime_shell-0.0.5.dist-info/METADATA
p4runtime_shell-0.0.5.dist-info/WHEEL
p4runtime_shell-0.0.5.dist-info/top_level.txt
p4runtime_shell-0.0.5.dist-info/RECORD
