Metadata-Version: 2.4
Name: p4runtime-shell
Version: 0.0.5
Summary: The P4Runtime shell
Home-page: https://github.com/p4lang/p4runtime-shell
Author: P4 API Working Group
Author-email: p4-api@lists.p4.org
License: Apache-2.0
Classifier: License :: OSI Approved :: Apache Software License
Classifier: Programming Language :: Python
Classifier: Programming Language :: Python :: 3
Requires-Python: >=3.6
License-File: LICENSE
Requires-Dist: jedi==0.17.2
Requires-Dist: ipython==7.31.*,>=7.31.1; python_version >= "3.7"
Requires-Dist: ipython==7.16.*,>=7.16.3; python_version < "3.7"
Requires-Dist: protobuf<3.21.0,>=3.15.0
Requires-Dist: grpcio>=1.35.0
Requires-Dist: p4runtime==1.4.1
Dynamic: license-file
